{
    "名前": "荒瀧一斗",
    "レアリティ": 5,
    "武器": "両手剣",
    "元素": "岩",
    "ステータス": {
        "基礎HP": {
            "80": 11345,
            "80+": 11954,
            "90": 12858
        },
        "基礎攻撃力": {
            "80": 200,
            "80+": 211,
            "90": 227
        },
        "基礎防御力": {
            "80": 846,
            "80+": 892,
            "90": 959
        },
        "会心率": {
            "80": 14.4,
            "80+": 19.2,
            "90": 19.2
        }
    },
    "通常攻撃": {
        "名前": "通常攻撃・喧嘩屋伝説",
        "説明": [
            "最大4段の連続攻撃を行う。"
        ],
        "詳細": [
            {
                "名前": "1段ダメージ",
                "数値": {
                    "1": "79.23%",
                    "2": "85.68%",
                    "3": "92.13%",
                    "4": "101.34%",
                    "5": "107.79%",
                    "6": "115.16%",
                    "7": "125.3%",
                    "8": "135.43%",
                    "9": "145.57%",
                    "10": "156.62%",
                    "11": "169.29%"
                }
            },
            {
                "名前": "2段ダメージ",
                "数値": {
                    "1": "76.37%",
                    "2": "82.58%",
                    "3": "88.8%",
                    "4": "97.68%",
                    "5": "103.9%",
                    "6": "111%",
                    "7": "120.77%",
                    "8": "130.54%",
                    "9": "140.3%",
                    "10": "150.96%",
                    "11": "163.17%"
                }
            },
            {
                "名前": "3段ダメージ",
                "数値": {
                    "1": "91.64%",
                    "2": "99.1%",
                    "3": "106.53%",
                    "4": "117.22%",
                    "5": "124.68%",
                    "6": "133.2%",
                    "7": "144.92%",
                    "8": "156.64%",
                    "9": "168.36%",
                    "10": "181.15%",
                    "11": "195.8%"
                }
            },
            {
                "名前": "4段ダメージ",
                "数値": {
                    "1": "117.22%",
                    "2": "126.77%",
                    "3": "136.31%",
                    "4": "149.94%",
                    "5": "159.48%",
                    "6": "170.39%",
                    "7": "185.38%",
                    "8": "200.37%",
                    "9": "215.37%",
                    "10": "231.72%",
                    "11": "250.47%"
                }
            }
        ]
    },
    "重撃": {
        "説明": [
            ""
        ],
        "詳細": [
            {
                "名前": "荒瀧逆袈裟連斬ダメージ",
                "数値": {
                    "1": "91.16%",
                    "2": "98.58%",
                    "3": "106%",
                    "4": "116.6%",
                    "5": "124.02%",
                    "6": "132.5%",
                    "7": "144.16%",
                    "8": "155.82%",
                    "9": "167.48%",
                    "10": "180.2%",
                    "11": "194.78%"
                }
            },
            {
                "名前": "荒瀧逆袈裟とどめダメージ",
                "数値": {
                    "1": "190.92%",
                    "2": "206.46%",
                    "3": "222%",
                    "4": "244.2%",
                    "5": "259.74%",
                    "6": "277.5%",
                    "7": "301.92%",
                    "8": "326.34%",
                    "9": "350.76%",
                    "10": "377.4%",
                    "11": "407.93%"
                }
            },
            {
                "名前": "左一文字斬りダメージ",
                "数値": {
                    "1": "90.47%",
                    "2": "97.84%",
                    "3": "105.2%",
                    "4": "115.72%",
                    "5": "123.08%",
                    "6": "131.5%",
                    "7": "143.07%",
                    "8": "154.64%",
                    "9": "166.22%",
                    "10": "178.84%",
                    "11": "193.31%"
                }
            }
        ]
    },
    "落下攻撃": {
        "説明": "空中から落下し地面に衝撃を与える。経路上の敵を攻撃し、落下時に範囲ダメージを与える。",
        "詳細": [
            {
                "名前": "落下期間のダメージ",
                "種類": "落下攻撃ダメージ",
                "数値": {
                    "1": "81.38%",
                    "2": "88.49%",
                    "3": "95.16%",
                    "4": "104.67%",
                    "5": "111.33%",
                    "6": "118.94%",
                    "7": "129.41%",
                    "8": "139.88%",
                    "9": "150.33%",
                    "10": "161.76%",
                    "11": "173.18%"
                }
            },
            {
                "名前": "低空落下攻撃ダメージ",
                "種類": "落下攻撃ダメージ",
                "数値": {
                    "1": "163.63%",
                    "2": "176.95%",
                    "3": "190.27%",
                    "4": "209.3%",
                    "5": "222.62%",
                    "6": "237.84%",
                    "7": "258.77%",
                    "8": "279.7%",
                    "9": "300.6%",
                    "10": "323.46%",
                    "11": "346.29%"
                }
            },
            {
                "名前": "高空落下攻撃ダメージ",
                "種類": "落下攻撃ダメージ",
                "数値": {
                    "1": "204.39%",
                    "2": "221.02%",
                    "3": "237.66%",
                    "4": "261.42%",
                    "5": "278.06%",
                    "6": "297.07%",
                    "7": "323.21%",
                    "8": "349.36%",
                    "9": "375.5%",
                    "10": "404.02%",
                    "11": "432.54%"
                }
            }
        ]
    },
    "元素スキル": {
        "名前": "魔殺絶技・岩牛発破！",
        "説明": "",
        "詳細": [
            {
                "名前": "スキルダメージ",
                "数値": {
                    "1": "307.2%",
                    "2": "330.24%",
                    "3": "353.28%",
                    "4": "384%",
                    "5": "407.04%",
                    "6": "430.08%",
                    "7": "460.8%",
                    "8": "491.52%",
                    "9": "522.24%",
                    "10": "552.96%",
                    "11": "583.68%",
                    "12": "614.4%",
                    "13": "652.8%"
                }
            },
            {
                "名前": "HP継承",
                "種類": "元素創造物HP",
                "数値": "100%HP上限"
            }
        ]
    },
    "元素爆発": {
        "名前": "最凶鬼王・一斗轟臨！！",
        "説明": [
            ""
        ],
        "詳細": [
            {
                "条件": "憤怒の鬼王",
                "名前": "攻撃力アップ",
                "種類": "攻撃力",
                "数値": {
                    "1": "57.6%防御力",
                    "2": "61.92%防御力",
                    "3": "66.24%防御力",
                    "4": "72%防御力",
                    "5": "76.32%防御力",
                    "6": "80.64%防御力",
                    "7": "86.4%防御力",
                    "8": "92.16%防御力",
                    "9": "97.92%防御力",
                    "10": "103.68%防御力",
                    "11": "109.44%防御力",
                    "12": "115.2%防御力",
                    "13": "122.4%防御力",
                    "14": "129.6%防御力"
                }
            },
            {
                "条件": "憤怒の鬼王",
                "種類": "岩元素付与"
            },
            {
                "条件": "憤怒の鬼王",
                "種類": "全元素耐性",
                "数値": -20
            },
            {
                "条件": "憤怒の鬼王",
                "種類": "物理耐性",
                "数値": -20
            }
        ]
    },
    "その他天賦": [
        {
            "名前": "荒瀧第一",
            "種類": "固有天賦",
            "説明": [
                ""
            ]
        },
        {
            "名前": "赤鬼の血",
            "種類": "固有天賦",
            "説明": [
                ""
            ],
            "詳細": [
                {
                    "対象": "重撃ダメージ.荒瀧逆袈裟連斬ダメージ",
                    "種類": "重撃ダメージアップ",
                    "数値": "35%防御力"
                },
                {
                    "対象": "重撃ダメージ.荒瀧逆袈裟とどめダメージ",
                    "種類": "重撃ダメージアップ",
                    "数値": "35%防御力"
                }
            ]
        },
        {
            "名前": "乾裂枝砕き",
            "種類": "固有天賦",
            "説明": ""
        }
    ],
    "命ノ星座": {
        "1": {
            "名前": "知らぬなら、聞かせてやろう",
            "説明": [
                ""
            ]
        },
        "2": {
            "名前": "衆よ集いて、山岳倒し",
            "説明": [
                ""
            ]
        },
        "3": {
            "名前": "牛王跨げば、水陸自在",
            "説明": [
                "魔殺絶技・岩牛発破！のスキルLv+3。",
                "最大Lv.15まで。"
            ]
        },
        "4": {
            "名前": "奉行牢獄、御食事処",
            "説明": [
                ""
            ]
        },
        "5": {
            "名前": "花坂十年、轟く我が名",
            "説明": [
                "最凶鬼王・一斗轟臨！！のスキルLv.+3。",
                "最大Lv.15まで"
            ]
        },
        "6": {
            "名前": "傾奇の張本、荒瀧一斗",
            "説明": [
                ""
            ],
            "詳細": [
                {
                    "対象": "重撃ダメージ",
                    "種類": "会心ダメージ",
                    "数値": 70
                }
            ]
        }
    },
    "おすすめセット": {
        "赤角石塵滅砕 華館夢醒形骸記 [防岩率]": {
            "武器": "赤角石塵滅砕",
            "聖遺物メイン効果3": "5_防御力%",
            "聖遺物メイン効果4": "5_岩元素ダメージバフ",
            "聖遺物メイン効果5": "5_会心率",
            "聖遺物セット効果1": "華館夢醒形骸記",
            "聖遺物セット効果2": "華館夢醒形骸記",
            "聖遺物優先するサブ効果1": "会心率",
            "聖遺物優先するサブ効果2": "会心ダメージ",
            "聖遺物優先するサブ効果3": "防御力%"
        },
        "螭龍の剣 華館夢醒形骸記 [防岩ダ]": {
            "武器": "螭龍の剣",
            "聖遺物メイン効果3": "5_防御力%",
            "聖遺物メイン効果4": "5_岩元素ダメージバフ",
            "聖遺物メイン効果5": "5_会心ダメージ",
            "聖遺物セット効果1": "華館夢醒形骸記",
            "聖遺物セット効果2": "華館夢醒形骸記",
            "聖遺物優先するサブ効果1": "会心率",
            "聖遺物優先するサブ効果2": "会心ダメージ",
            "聖遺物優先するサブ効果3": "防御力%"
        },
        "天空の傲 華館夢醒形骸記 [防岩率]": {
            "武器": "天空の傲",
            "聖遺物メイン効果3": "5_防御力%",
            "聖遺物メイン効果4": "5_岩元素ダメージバフ",
            "聖遺物メイン効果5": "5_会心率",
            "聖遺物セット効果1": "華館夢醒形骸記",
            "聖遺物セット効果2": "華館夢醒形骸記",
            "聖遺物優先するサブ効果1": "会心ダメージ",
            "聖遺物優先するサブ効果2": "会心率",
            "聖遺物優先するサブ効果3": "防御力%"
        },
        "西風大剣 華館夢醒形骸記 [防岩率]": {
            "武器": "螭龍の剣",
            "聖遺物メイン効果3": "5_防御力%",
            "聖遺物メイン効果4": "5_岩元素ダメージバフ",
            "聖遺物メイン効果5": "5_会心率",
            "聖遺物セット効果1": "華館夢醒形骸記",
            "聖遺物セット効果2": "華館夢醒形骸記",
            "聖遺物優先するサブ効果1": "会心ダメージ",
            "聖遺物優先するサブ効果2": "会心率",
            "聖遺物優先するサブ効果3": "防御力%"
        },
        "赤角石塵滅砕 逆飛びの流星 [防岩率]": {
            "武器": "赤角石塵滅砕",
            "聖遺物メイン効果3": "5_防御力%",
            "聖遺物メイン効果4": "5_岩元素ダメージバフ",
            "聖遺物メイン効果5": "5_会心率",
            "聖遺物セット効果1": "逆飛びの流星",
            "聖遺物セット効果2": "逆飛びの流星",
            "聖遺物優先するサブ効果1": "会心率",
            "聖遺物優先するサブ効果2": "会心ダメージ",
            "聖遺物優先するサブ効果3": "防御力%"
        },
        "螭龍の剣 逆飛びの流星 [防岩ダ]": {
            "武器": "螭龍の剣",
            "聖遺物メイン効果3": "5_防御力%",
            "聖遺物メイン効果4": "5_岩元素ダメージバフ",
            "聖遺物メイン効果5": "5_会心ダメージ",
            "聖遺物セット効果1": "逆飛びの流星",
            "聖遺物セット効果2": "逆飛びの流星",
            "聖遺物優先するサブ効果1": "会心率",
            "聖遺物優先するサブ効果2": "会心ダメージ",
            "聖遺物優先するサブ効果3": "防御力%"
        },
        "白影の剣 逆飛びの流星 [防岩率]": {
            "武器": "白影の剣",
            "聖遺物メイン効果3": "5_防御力%",
            "聖遺物メイン効果4": "5_岩元素ダメージバフ",
            "聖遺物メイン効果5": "5_会心率",
            "聖遺物セット効果1": "逆飛びの流星",
            "聖遺物セット効果2": "逆飛びの流星",
            "聖遺物優先するサブ効果1": "会心ダメージ",
            "聖遺物優先するサブ効果2": "会心率",
            "聖遺物優先するサブ効果3": "防御力%"
        },
        "西風大剣 逆飛びの流星 [防岩率]": {
            "武器": "西風大剣",
            "聖遺物メイン効果3": "5_防御力%",
            "聖遺物メイン効果4": "5_岩元素ダメージバフ",
            "聖遺物メイン効果5": "5_会心率",
            "聖遺物セット効果1": "逆飛びの流星",
            "聖遺物セット効果2": "逆飛びの流星",
            "聖遺物優先するサブ効果1": "会心ダメージ",
            "聖遺物優先するサブ効果2": "会心率",
            "聖遺物優先するサブ効果3": "防御力%"
        }
    }
}